{
  "一年级": [
    "语文",
    "数学",
    "英语"
  ],
  "二年级": [
    "语文",
    "数学",
    "英语"
  ],
  "三年级": [
    "语文",
    "数学",
    "英语"
  ],
  "四年级": [
    "语文",
    "数学",
    "英语"
  ],
  "五年级": [
    "语文",
    "数学",
    "英语"
  ],
  "六年级": [
    "语文",
    "数学",
    "英语"
  ],
  "初一": [
    "语文",
    "数学",
    "英语",
    "政治",
    "地理",
    "历史",
    "生物"
  ],
  "初二": [
    "语文",
    "数学",
    "英语",
    "政治",
    "地理",
    "历史",
    "物理",
    "生物"
  ],
  "初三": [
    "语文",
    "数学",
    "英语",
    "政治",
    "地理",
    "历史",
    "物理",
    "化学",
    "生物"
  ],
  "高一": [
    "语文",
    "数学",
    "英语",
    "政治",
    "地理",
    "历史",
    "物理",
    "化学",
    "生物"
  ],
  "高二": [
    "语文",
    "数学",
    "英语",
    "政治",
    "地理",
    "历史",
    "物理",
    "化学",
    "生物"
  ],
  "高三": [
    "语文",
    "数学",
    "英语",
    "政治",
    "地理",
    "历史",
    "物理",
    "化学",
    "生物"
  ]
}